README.md
setup.py
scMethQ/__init__.py
scMethQ/_utils.py
scMethQ/_version.py
scMethQ/genome.py
scMethQ/get.py
scMethQ/io.py
scMethQ/logging.py
scMethQ/settings.py
scMethQ/dmr/__init__.py
scMethQ/dmr/annotation.py
scMethQ/dmr/dmg.py
scMethQ/dmr/enrichment.py
scMethQ/dmr/feature_select.py
scMethQ/dmr/hvf.py
scMethQ/dmr/motif.py
scMethQ/plotting/__init__.py
scMethQ/plotting/_palette.py
scMethQ/plotting/_profile.py
scMethQ/plotting/_scatter.py
scMethQ/plotting/basic.py
scMethQ/plotting/dendrogram.py
scMethQ/plotting/enrichment.py
scMethQ/plotting/heatmap.py
scMethQ/plotting/marker.py
scMethQ/plotting/plot_annotation.py
scMethQ/plotting/plot_stat.py
scMethQ/plotting/tsne.py
scMethQ/preprocessing/__init__.py
scMethQ/preprocessing/_build.py
scMethQ/preprocessing/_format.py
scMethQ/preprocessing/_methylation_level.py
scMethQ/preprocessing/adaptive_smooth.py
scMethQ/preprocessing/denovo.py
scMethQ/preprocessing/feature.py
scMethQ/preprocessing/scm.py
scmethq.egg-info/PKG-INFO
scmethq.egg-info/SOURCES.txt
scmethq.egg-info/dependency_links.txt
scmethq.egg-info/not-zip-safe
scmethq.egg-info/top_level.txt