Metadata-Version: 1.0
Name: scmethq
Version: 0.1.0
Summary: scMethQ
Home-page: UNKNOWN
Author: UNKNOWN
Author-email: UNKNOWN
License: UNKNOWN
Platform: UNKNOWN
